facedbook/__init__.py
facedbook/__main__.py
facedbook/encoder.py
facedbook/faces.py
facedbook/feelings.py
facedbook/stories.py
facedbook-0.1.4.dist-info/LICENSE
facedbook-0.1.4.dist-info/METADATA
facedbook-0.1.4.dist-info/WHEEL
facedbook-0.1.4.dist-info/entry_points.txt
facedbook-0.1.4.dist-info/top_level.txt
facedbook-0.1.4.dist-info/RECORD
