Metadata-Version: 2.2
Name: facedbook
Version: 0.1.4
Summary: A package that incorporates kaomojis for the user.
Author: Team Everything
License:                     GNU GENERAL PUBLIC LICENSE
Project-URL: Homepage, https://github.com/software-students-spring2025/3-python-package-everything
Project-URL: Repository, https://github.com/software-students-spring2025/3-python-package-everything
Project-URL: Bug Tracker, https://github.com/software-students-spring2025/3-python-package-everything/issues
Keywords: python,package,build,tutorial
Classifier: Programming Language :: Python :: 3
Classifier: Intended Audience :: Education
Classifier: License :: OSI Approved :: GNU General Public License v3 (GPLv3)
Classifier: Operating System :: OS Independent
Requires-Python: >=3.7
License-File: LICENSE
Provides-Extra: dev
Requires-Dist: pytest; extra == "dev"
